[
  {
    "owner": "123@mail.ru",
    "msg": "123",
    "colorname": ""
  },
  {
    "owner": "123@mail.ru",
    "msg": "123",
    "colorname": ""
  },
  {
    "owner": "123@mail.ru",
    "msg": "a",
    "colorname": ""
  },
  {
    "owner": "123@mail.ru",
    "msg": "пж не пишите Е*аные var'ы в коде  :happy:",
    "colorname": ""
  },
  {
    "owner": "Федя",
    "msg": "п",
    "colorname": ""
  },
  {
    "owner": "Федя",
    "msg": "к",
    "colorname": ""
  },
  {
    "owner": "LAGZYA",
    "msg": "чсм",
    "colorname": ""
  },
  {
    "owner": "LAGZYA",
    "msg": "чсмм",
    "colorname": ""
  },
  {
    "owner": "LAGZYA",
    "msg": "чс",
    "colorname": ""
  },
  {
    "owner": "LAGZYA",
    "msg": "мчс",
    "colorname": ""
  },
  {
    "owner": "LAGZYA",
    "msg": "м",
    "colorname": ""
  },
  {
    "owner": "LAGZYA",
    "msg": "чс",
    "colorname": ""
  },
  {
    "owner": "LAGZYA",
    "msg": "мч",
    "colorname": ""
  },
  {
    "owner": "LAGZYA",
    "msg": "счсм",
    "colorname": ""
  },
  {
    "owner": "LAGZYA",
    "msg": "чсм",
    "colorname": ""
  },
  {
    "owner": "Федя",
    "msg": "лоо",
    "colorname": ""
  },
  {
    "owner": "123@mail.ru",
    "msg": "работает?",
    "colorname": ""
  },
  {
    "owner": "123@mail.ru",
    "msg": "Нет?",
    "colorname": ""
  },
  {
    "owner": "123@mail.ru",
    "msg": "эээээй",
    "colorname": ""
  },
  {
    "owner": "Федя",
    "msg": " :happy:",
    "colorname": ""
  },
  {
    "owner": "123@mail.ru",
    "msg": "a",
    "colorname": ""
  },
  {
    "owner": "123@mail.ru",
    "msg": "asa",
    "colorname": ""
  },
  {
    "owner": "123@mail.ru",
    "msg": "sss",
    "colorname": ""
  },
  {
    "owner": "123@mail.ru",
    "msg": "sssa",
    "colorname": ""
  },
  {
    "owner": "LAGZYA",
    "msg": "3232",
    "colorname": ""
  },
  {
    "owner": "LAGZYA",
    "msg": "3",
    "colorname": ""
  },
  {
    "owner": "LAGZYA",
    "msg": "23",
    "colorname": ""
  },
  {
    "owner": "LAGZYA",
    "msg": "23",
    "colorname": ""
  },
  {
    "owner": "123@mail.ru",
    "msg": "-",
    "colorname": ""
  },
  {
    "owner": "Игорь",
    "msg": "/start",
    "colorname": ""
  },
  {
    "owner": "Administratorr",
    "msg": "fdf",
    "colorname": ""
  },
  {
    "owner": "Administratorr",
    "msg": "vxcv",
    "colorname": ""
  },
  {
    "owner": "Игорь",
    "msg": "Anal",
    "colorname": ""
  },
  {
    "owner": "Administratorr",
    "msg": "КОГДА ПОВЫШЕНИЕ?",
    "colorname": ""
  },
  {
    "owner": "123@mail.ru",
    "msg": "Нужна кнопка бана",
    "colorname": ""
  },
  {
    "owner": "Игорь",
    "msg": "Зп когда",
    "colorname": ""
  },
  {
    "owner": "Administratorr",
    "msg": "Есть мут",
    "colorname": ""
  },
  {
    "owner": "Administratorr",
    "msg": "команда",
    "colorname": ""
  },
  {
    "owner": "LAGZYA",
    "msg": "Предложения ахуенные",
    "colorname": ""
  },
  {
    "owner": "Игорь",
    "msg": "👍",
    "colorname": ""
  },
  {
    "owner": "LAGZYA",
    "msg": "орор",
    "colorname": ""
  },
  {
    "owner": "Administratorr",
    "msg": "ff",
    "colorname": "red"
  },
  {
    "owner": "Administratorr",
    "msg": "v",
    "colorname": "red"
  },
  {
    "owner": "Игорь",
    "msg": "😅",
    "colorname": ""
  },
  {
    "owner": "Игорь",
    "msg": "😘",
    "colorname": ""
  },
  {
    "owner": "Игорь",
    "msg": "🫡",
    "colorname": ""
  },
  {
    "owner": "Administratorr",
    "msg": "fsdg",
    "colorname": ""
  },
  {
    "owner": "Administratorr",
    "msg": "c",
    "colorname": ""
  },
  {
    "owner": "Игорь",
    "msg": "👌👈",
    "colorname": ""
  },
  {
    "owner": "Administratorr",
    "msg": "fgdg",
    "colorname": ""
  },
  {
    "owner": "Administratorr",
    "msg": "dgb",
    "colorname": ""
  },
  {
    "owner": "Игорь",
    "msg": "прогресс пошёл",
    "colorname": ""
  },
  {
    "owner": "Игорь",
    "msg": "Пися в попе",
    "colorname": ""
  },
  {
    "owner": "LAGZYA",
    "msg": "Таоаов",
    "colorname": ""
  },
  {
    "owner": "LAGZYA",
    "msg": "Ьвлвлтв",
    "colorname": ""
  },
  {
    "owner": "LAGZYA",
    "msg": "Ововов",
    "colorname": ""
  },
  {
    "owner": "LAGZYA",
    "msg": "Твовлв",
    "colorname": ""
  },
  {
    "owner": "Administratorr",
    "msg": "dfg",
    "colorname": ""
  },
  {
    "owner": "Administratorr",
    "msg": "dv",
    "colorname": ""
  },
  {
    "owner": "Administratorr",
    "msg": "v",
    "colorname": ""
  },
  {
    "owner": "Administratorr",
    "msg": "v",
    "colorname": ""
  },
  {
    "owner": "Administratorr",
    "msg": "v",
    "colorname": ""
  },
  {
    "owner": "Administratorr",
    "msg": "v\\",
    "colorname": ""
  },
  {
    "owner": "LAGZYA",
    "msg": "Раоов",
    "colorname": ""
  },
  {
    "owner": "LAGZYA",
    "msg": "Воов",
    "colorname": ""
  },
  {
    "owner": "LAGZYA",
    "msg": "Ир",
    "colorname": ""
  },
  {
    "owner": "LAGZYA",
    "msg": "Прв",
    "colorname": ""
  },
  {
    "owner": "LAGZYA",
    "msg": "Шор",
    "colorname": ""
  },
  {
    "owner": "123@mail.ru",
    "msg": "ыы",
    "colorname": ""
  },
  {
    "owner": "LAGZYA",
    "msg": " :happy: :happy: :happy: :happy:",
    "colorname": ""
  },
  {
    "owner": "LAGZYA",
    "msg": " :happy: :happy: :happy:",
    "colorname": ""
  },
  {
    "owner": "123@mail.ru",
    "msg": "можешь список команд поправить",
    "colorname": ""
  },
  {
    "owner": "123@mail.ru",
    "msg": "чтобы актульным был ",
    "colorname": ""
  },
  {
    "owner": "LAGZYA",
    "msg": "123",
    "colorname": ""
  },
  {
    "owner": "Федя",
    "msg": "huoi",
    "colorname": ""
  },
  {
    "owner": "Федя",
    "msg": " /join 1 ножницы",
    "colorname": ""
  },
  {
    "owner": "123@mail.ru",
    "msg": "о бля ",
    "colorname": ""
  },
  {
    "owner": "123@mail.ru",
    "msg": "придумал",
    "colorname": ""
  },
  {
    "owner": "Федя",
    "msg": "что",
    "colorname": ""
  },
  {
    "owner": "123@mail.ru",
    "msg": "сейчас ",
    "colorname": ""
  },
  {
    "owner": "LAGZYA",
    "msg": "23",
    "colorname": ""
  },
  {
    "owner": "Ихарь",
    "msg": "прглр",
    "colorname": ""
  },
  {
    "owner": "123@mail.ru",
    "msg": "не оставь ту зелёную полоску ",
    "colorname": ""
  },
  {
    "owner": "Ихарь",
    "msg": "\\э",
    "colorname": ""
  },
  {
    "owner": "Ихарь",
    "msg": "о\\э",
    "colorname": ""
  },
  {
    "owner": "123@mail.ru",
    "msg": "она стильно смотрелась",
    "colorname": ""
  },
  {
    "owner": "Ихарь",
    "msg": "нее хуйня",
    "colorname": ""
  },
  {
    "owner": "Никита",
    "msg": "Я пытаюсь ее заставить двигаться",
    "colorname": ""
  },
  {
    "owner": "Ихарь",
    "msg": " :happy:",
    "colorname": ""
  },
  {
    "owner": "LAGZYA",
    "msg": "123231",
    "colorname": ""
  },
  {
    "owner": "LAGZYA",
    "msg": "123",
    "colorname": ""
  },
  {
    "owner": "LAGZYA",
    "msg": "321",
    "colorname": ""
  },
  {
    "owner": "LAGZYA",
    "msg": "321",
    "colorname": ""
  },
  {
    "owner": "LAGZYA",
    "msg": "321",
    "colorname": ""
  },
  {
    "owner": "LAGZYA",
    "msg": "kjkjo",
    "colorname": ""
  },
  {
    "owner": "Administratorr",
    "msg": "gdg",
    "colorname": ""
  },
  {
    "owner": "LAGZYA",
    "msg": "hjgugyug\\",
    "colorname": ""
  },
  {
    "owner": "Administratorr",
    "msg": "fdsv",
    "colorname": ""
  },
  {
    "owner": "Administratorr",
    "msg": "xv",
    "colorname": ""
  },
  {
    "owner": "Administratorr",
    "msg": "fsf",
    "colorname": ""
  },
  {
    "owner": "Administratorr",
    "msg": "ew",
    "colorname": ""
  },
  {
    "owner": "123@mail.ru",
    "msg": "сделал таки ls?",
    "colorname": ""
  },
  {
    "owner": "Ихарь",
    "msg": "ыаыа",
    "colorname": ""
  },
  {
    "owner": "LAGZYA",
    "msg": "234",
    "colorname": ""
  },
  {
    "owner": "LAGZYA",
    "msg": "432",
    "colorname": ""
  },
  {
    "owner": "LAGZYA",
    "msg": "Рр",
    "colorname": ""
  },
  {
    "owner": "123@mail.ru",
    "msg": "dscdsd",
    "colorname": ""
  },
  {
    "owner": "Никита",
    "msg": "Верните регистрацию",
    "colorname": ""
  },
  {
    "owner": "Никита",
    "msg": "Спасибо!",
    "colorname": ""
  },
  {
    "owner": "123@mail.ru",
    "msg": "sdsdsd",
    "colorname": ""
  }
]